<annotation>
	<folder>Capture</folder>
	<filename>Image_batch_07_00136.jpg</filename>
	<path>D:\Pure Codec\x64\Capture\Image_batch_07_00136.jpg</path>
	<source>
		<database>Unknown</database>
	</source>
	<size>
		<width>1920</width>
		<height>1080</height>
		<depth>3</depth>
	</size>
	<segmented>0</segmented>
	<object>
		<name>樱</name>
		<pose>Unspecified</pose>
		<truncated>1</truncated>
		<difficult>0</difficult>
		<bndbox>
			<xmin>1326</xmin>
			<ymin>818</ymin>
			<xmax>1539</xmax>
			<ymax>1080</ymax>
		</bndbox>
	</object>
	<object>
		<name>桐</name>
		<pose>Unspecified</pose>
		<truncated>1</truncated>
		<difficult>0</difficult>
		<bndbox>
			<xmin>1414</xmin>
			<ymin>649</ymin>
			<xmax>1540</xmax>
			<ymax>1080</ymax>
		</bndbox>
	</object>
	<object>
		<name>皋</name>
		<pose>Unspecified</pose>
		<truncated>1</truncated>
		<difficult>0</difficult>
		<bndbox>
			<xmin>1301</xmin>
			<ymin>687</ymin>
			<xmax>1412</xmax>
			<ymax>1080</ymax>
		</bndbox>
	</object>
	<object>
		<name>瓜之介</name>
		<pose>Unspecified</pose>
		<truncated>0</truncated>
		<difficult>0</difficult>
		<bndbox>
			<xmin>1277</xmin>
			<ymin>954</ymin>
			<xmax>1372</xmax>
			<ymax>1048</ymax>
		</bndbox>
	</object>
	<object>
		<name>柚</name>
		<pose>Unspecified</pose>
		<truncated>1</truncated>
		<difficult>0</difficult>
		<bndbox>
			<xmin>1154</xmin>
			<ymin>753</ymin>
			<xmax>1401</xmax>
			<ymax>1080</ymax>
		</bndbox>
	</object>
	<object>
		<name>莲</name>
		<pose>Unspecified</pose>
		<truncated>1</truncated>
		<difficult>0</difficult>
		<bndbox>
			<xmin>1064</xmin>
			<ymin>790</ymin>
			<xmax>1223</xmax>
			<ymax>1080</ymax>
		</bndbox>
	</object>
	<object>
		<name>枣</name>
		<pose>Unspecified</pose>
		<truncated>1</truncated>
		<difficult>0</difficult>
		<bndbox>
			<xmin>1026</xmin>
			<ymin>689</ymin>
			<xmax>1151</xmax>
			<ymax>1080</ymax>
		</bndbox>
	</object>
	<object>
		<name>阿菊</name>
		<pose>Unspecified</pose>
		<truncated>0</truncated>
		<difficult>0</difficult>
		<bndbox>
			<xmin>1156</xmin>
			<ymin>873</ymin>
			<xmax>1189</xmax>
			<ymax>922</ymax>
		</bndbox>
	</object>
</annotation>
