<annotation>
	<folder>kanohana_img</folder>
	<filename>Image_batch_01_00140.jpg</filename>
	<path>D:\Users\TWD\Desktop\kanohana_img\Image_batch_01_00140.jpg</path>
	<source>
		<database>Unknown</database>
	</source>
	<size>
		<width>1920</width>
		<height>1080</height>
		<depth>3</depth>
	</size>
	<segmented>0</segmented>
	<object>
		<name>柚</name>
		<pose>Unspecified</pose>
		<truncated>0</truncated>
		<difficult>0</difficult>
		<bndbox>
			<xmin>589</xmin>
			<ymin>643</ymin>
			<xmax>1149</xmax>
			<ymax>948</ymax>
		</bndbox>
	</object>
	<object>
		<name>莲</name>
		<pose>Unspecified</pose>
		<truncated>0</truncated>
		<difficult>0</difficult>
		<bndbox>
			<xmin>200</xmin>
			<ymin>204</ymin>
			<xmax>393</xmax>
			<ymax>920</ymax>
		</bndbox>
	</object>
</annotation>
