<annotation>
	<folder>kanohana_img</folder>
	<filename>Image_batch_01_00002.jpg</filename>
	<path>D:\Users\TWD\Desktop\kanohana_img\Image_batch_01_00002.jpg</path>
	<source>
		<database>Unknown</database>
	</source>
	<size>
		<width>1920</width>
		<height>1080</height>
		<depth>3</depth>
	</size>
	<segmented>0</segmented>
	<object>
		<name>八百比丘尼</name>
		<pose>Unspecified</pose>
		<truncated>1</truncated>
		<difficult>0</difficult>
		<bndbox>
			<xmin>517</xmin>
			<ymin>140</ymin>
			<xmax>974</xmax>
			<ymax>1080</ymax>
		</bndbox>
	</object>
	<object>
		<name>柚</name>
		<pose>Unspecified</pose>
		<truncated>1</truncated>
		<difficult>0</difficult>
		<bndbox>
			<xmin>924</xmin>
			<ymin>254</ymin>
			<xmax>1513</xmax>
			<ymax>1080</ymax>
		</bndbox>
	</object>
</annotation>
